eo4eu_data_utils/__init__.py
eo4eu_data_utils/config/__init__.py
eo4eu_data_utils/config/config.py
eo4eu_data_utils/config/config_source.py
eo4eu_data_utils/config/filler.py
eo4eu_data_utils/config/logs.py
eo4eu_data_utils/config/model.py
eo4eu_data_utils/config/source.py
eo4eu_data_utils/config/utils.py
eo4eu_data_utils/drivers/__init__.py
eo4eu_data_utils/drivers/interface.py
eo4eu_data_utils/drivers/local.py
eo4eu_data_utils/drivers/s3.py
eo4eu_data_utils/helpers/__init__.py
eo4eu_data_utils/helpers/data.py
eo4eu_data_utils/helpers/format.py
eo4eu_data_utils/helpers/logs.py
eo4eu_data_utils/helpers/s3.py
eo4eu_data_utils/helpers/unpack.py
eo4eu_data_utils/metainfo/__init__.py
eo4eu_data_utils/metainfo/ds_metainfo.py
eo4eu_data_utils/metainfo/logs.py
eo4eu_data_utils/pipeline/__init__.py
eo4eu_data_utils/pipeline/actions.py
eo4eu_data_utils/pipeline/interface.py
eo4eu_data_utils/pipeline/pipeline.py
eo4eu_data_utils/settings/__init__.py
eo4eu_data_utils/settings/data.py
eo4eu_data_utils/settings/safe_dict.py
eo4eu_data_utils/stream/__init__.py
eo4eu_data_utils/stream/actions.py
eo4eu_data_utils/stream/drivers.py
eo4eu_data_utils/stream/logs.py
eo4eu_data_utils/stream/model.py
eo4eu_data_utils/stream/stream.py
eo4eu_data_utils-0.26.8.dist-info/METADATA
eo4eu_data_utils-0.26.8.dist-info/WHEEL
eo4eu_data_utils-0.26.8.dist-info/top_level.txt
eo4eu_data_utils-0.26.8.dist-info/RECORD
