Metadata-Version: 2.4
Name: eo4eu_data_utils
Version: 0.26.8
Summary: General data access utilities for EO4EU
Author-email: Apollon Grigoras <apollon@uoa.gr>
Classifier: Programming Language :: Python :: 3
Classifier: Programming Language :: Python :: 3.10
Classifier: Programming Language :: Python :: 3.11
Classifier: Programming Language :: Python :: 3.12
Classifier: Operating System :: OS Independent
Requires-Python: >=3.10
Requires-Dist: eo4eu_base_utils>=0.4.6
Provides-Extra: s3
Requires-Dist: boto3~=1.26.137; python_version <= "3.11" and extra == "s3"
Requires-Dist: boto3<=1.35.99,>=1.26.137; python_version >= "3.12" and extra == "s3"
Provides-Extra: cloudpath
Requires-Dist: cloudpathlib~=0.15.1; python_version <= "3.11" and extra == "cloudpath"
Requires-Dist: cloudpathlib>=0.15.1; python_version >= "3.12" and extra == "cloudpath"
Provides-Extra: full
Requires-Dist: eo4eu_data_utils[cloudpath,s3]; extra == "full"
